mines_data_engineering/__init__.py
mines_data_engineering/container.py
mines_data_engineering/data_generation.py
mines_data_engineering/relalg.py
mines_data_engineering/sample_tables.py
mines_data_engineering/storage.py
mines_data_engineering/util.py
mines_data_engineering-0.1.7.dist-info/WHEEL
mines_data_engineering-0.1.7.dist-info/METADATA
mines_data_engineering-0.1.7.dist-info/RECORD
